okx/Account.py
okx/BlockTrading.py
okx/Convert.py
okx/CopyTrading.py
okx/FDBroker.py
okx/Funding.py
okx/Grid.py
okx/MarketData.py
okx/PublicData.py
okx/SpreadTrading.py
okx/Status.py
okx/SubAccount.py
okx/Trade.py
okx/TradingData.py
okx/__init__.py
okx/consts.py
okx/exceptions.py
okx/okxclient.py
okx/utils.py
okx/Finance/EthStaking.py
okx/Finance/FlexibleLoan.py
okx/Finance/Savings.py
okx/Finance/SolStaking.py
okx/Finance/StakingDefi.py
okx/Finance/__init__.py
okx/websocket/WebSocketFactory.py
okx/websocket/WsPrivateAsync.py
okx/websocket/WsPublicAsync.py
okx/websocket/WsUtils.py
okx/websocket/__init__.py
python_okx-0.3.9.dist-info/METADATA
python_okx-0.3.9.dist-info/WHEEL
python_okx-0.3.9.dist-info/top_level.txt
python_okx-0.3.9.dist-info/RECORD
