Metadata-Version: 2.1
Name: python-okx
Version: 0.3.9
Summary: Python SDK for OKX
Home-page: https://okx.com/docs-v5/
Author: okxv5api
Author-email: api@okg.com
Classifier: Programming Language :: Python :: 3
Classifier: License :: OSI Approved :: MIT License
Classifier: Operating System :: OS Independent
Requires-Dist: importlib-metadata
Requires-Dist: httpx[http2]
Requires-Dist: keyring
Requires-Dist: loguru
Requires-Dist: requests
Requires-Dist: Twisted
Requires-Dist: pyOpenSSL
